{"book":"deuteronomy","chapter":30,"source":"Church Fathers (Public Domain)","verses":{"15":"Let us ponder the nature of life and of death. Life is the enjoyment of the gift of breath, death the deprivation of it. Further, this gift of breath is considered by most people as a good. And so life is this, the enjoyment of goods, but death is the divestiture of them. And Scripture says, “Behold, I have set before your face life and death, good and evil,” for it calls life good and death evil and attributes to each its proper deserts.","14":"But consider if perhaps all people participate in him insofar as he is Word. This is why the apostle teaches us that he is sought within the seekers by those who choose to find him. He says, “Do not say in your heart, ‘Who shall ascend into heaven?’ that is, to bring Christ down; or, ‘Who shall descend into the deep?’ that is, to bring Christ up again from the dead. But what does the Scripture say? The Word is near you, even in your mouth, and in your heart.” This is as though Christ and the Word which is sought are the same."}}