{"book":"2kings","chapter":21,"source":"Church Fathers (Public Domain)","verses":{"2-16":"For so Manasseh had perpetrated innumerable pollutions, having both stretched out his hands against the saints, and brought abominations into the temple, and filled the city with murders and wrought many other things beyond excuse; yet nevertheless after so long and so great wickedness, he washed away from himself all these things. How and in what matter? By repentance and self-examination. For there is no sin that does not yield and give way to the power of repentance, or rather to the grace of Christ. Since if we would but only change, we have him to assist us. ..."}}